[
    "{"t":"https://a.kontol.online/api/imageV2/t/1207390/thumb.jpg","w":350,"h":150},"pages":[{"t":"https://a.kontol.online/api/imageV2/i/1207390/1.jpg","w":1280,"h":548},{"t":"https://b.kontol.online/api/imageV2/i/1207390/2.jpg","w":1280,"h":179},{"t":"https://c.kontol.online/api/imageV2/i/1207390/3.jpg","w":1280,"h":862},{"t":"https://d.kontol.online/api/imageV2/i/1207390/4.jpg","w":1280,"h":1862},{"t":"https://e.kontol.online/api/imageV2/i/1207390/5.jpg","w":1280,"h":1868},{"t":"https://f.kontol.online/api/imageV2/i/1207390/6.jpg","w":1280,"h":1536},{"t":"https://g.kontol.online/api/imageV2/i/1207390/7.jpg","w":1280,"h":1898},{"t":"https://a.kontol.online/api/imageV2/i/1207390/8.jpg","w":1280,"h":1976},{"t":"https://b.kontol.online/api/imageV2/i/1207390/9.jpg","w":1280,"h":1972},{"t":"https://c.kontol.online/api/imageV2/i/1207390/10.jpg","w":1280,"h":1980},{"t":"https://d.kontol.online/api/imageV2/i/1207390/11.jpg","w":1280,"h":1973},{"t":"https://e.kontol.online/api/imageV2/i/1207390/12.jpg","w":1280,"h":1978},{"t":"https://f.kontol.online/api/imageV2/i/1207390/13.jpg","w":1280,"h":1976},{"t":"https://g.kontol.online/api/imageV2/i/1207390/14.jpg","w":1280,"h":1992},{"t":"https://a.kontol.online/api/imageV2/i/1207390/15.jpg","w":1280,"h":1979},{"t":"https://b.kontol.online/api/imageV2/i/1207390/16.jpg","w":1280,"h":1986},{"t":"https://c.kontol.online/api/imageV2/i/1207390/17.jpg","w":1280,"h":1979},{"t":"https://d.kontol.online/api/imageV2/i/1207390/18.jpg","w":1280,"h":1993},{"t":"https://e.kontol.online/api/imageV2/i/1207390/19.jpg","w":1280,"h":1984},{"t":"https://f.kontol.online/api/imageV2/i/1207390/20.jpg","w":1280,"h":1987},{"t":"https://g.kontol.online/api/imageV2/i/1207390/21.jpg","w":1280,"h":1983},{"t":"https://a.kontol.online/api/imageV2/i/1207390/22.jpg","w":1280,"h":1989},{"t":"https://b.kontol.online/api/imageV2/i/1207390/23.jpg","w":1280,"h":1989},{"t":"https://c.kontol.online/api/imageV2/i/1207390/24.jpg","w":1280,"h":1957},{"t":"https://d.kontol.online/api/imageV2/i/1207390/25.jpg","w":1280,"h":1945},{"t":"https://e.kontol.online/api/imageV2/i/1207390/26.jpg","w":1280,"h":1949},{"t":"https://f.kontol.online/api/imageV2/i/1207390/27.jpg","w":1280,"h":1946},{"t":"https://g.kontol.online/api/imageV2/i/1207390/28.jpg","w":1280,"h":1948},{"t":"https://a.kontol.online/api/imageV2/i/1207390/29.jpg","w":1280,"h":1944},{"t":"https://b.kontol.online/api/imageV2/i/1207390/30.jpg","w":1280,"h":1949},{"t":"https://c.kontol.online/api/imageV2/i/1207390/31.jpg","w":1280,"h":1951},{"t":"https://d.kontol.online/api/imageV2/i/1207390/32.jpg","w":1280,"h":1948},{"t":"https://e.kontol.online/api/imageV2/i/1207390/33.jpg","w":1280,"h":1946},{"t":"https://f.kontol.online/api/imageV2/i/1207390/34.jpg","w":1280,"h":1946},{"t":"https://g.kontol.online/api/imageV2/i/1207390/35.jpg","w":1280,"h":1948},{"t":"https://a.kontol.online/api/imageV2/i/1207390/36.jpg","w":1280,"h":1947},{"t":"https://b.kontol.online/api/imageV2/i/1207390/37.jpg","w":1280,"h":1946},{"t":"https://c.kontol.online/api/imageV2/i/1207390/38.jpg","w":1280,"h":1953},{"t":"https://d.kontol.online/api/imageV2/i/1207390/39.jpg","w":1280,"h":1949},{"t":"https://e.kontol.online/api/imageV2/i/1207390/40.jpg","w":1280,"h":1948},{"t":"https://f.kontol.online/api/imageV2/i/1207390/41.jpg","w":1280,"h":1953},{"t":"https://g.kontol.online/api/imageV2/i/1207390/42.jpg","w":1280,"h":1953},{"t":"https://a.kontol.online/api/imageV2/i/1207390/43.jpg","w":1280,"h":1954},{"t":"https://b.kontol.online/api/imageV2/i/1207390/44.jpg","w":1280,"h":1929},{"t":"https://c.kontol.online/api/imageV2/i/1207390/45.jpg","w":1280,"h":1925},{"t":"https://d.kontol.online/api/imageV2/i/1207390/46.jpg","w":1280,"h":1936},{"t":"https://e.kontol.online/api/imageV2/i/1207390/47.jpg","w":1280,"h":1932},{"t":"https://f.kontol.online/api/imageV2/i/1207390/48.jpg","w":1280,"h":1941},{"t":"https://g.kontol.online/api/imageV2/i/1207390/49.jpg","w":1280,"h":1935},{"t":"https://a.kontol.online/api/imageV2/i/1207390/50.jpg","w":1280,"h":1941},{"t":"https://b.kontol.online/api/imageV2/i/1207390/51.jpg","w":1280,"h":1942},{"t":"https://c.kontol.online/api/imageV2/i/1207390/52.jpg","w":1280,"h":1942},{"t":"https://d.kontol.online/api/imageV2/i/1207390/53.jpg","w":1280,"h":1943},{"t":"https://e.kontol.online/api/imageV2/i/1207390/54.jpg","w":1280,"h":1948},{"t":"https://f.kontol.online/api/imageV2/i/1207390/55.jpg","w":1280,"h":1956},{"t":"https://g.kontol.online/api/imageV2/i/1207390/56.jpg","w":1280,"h":1940},{"t":"https://a.kontol.online/api/imageV2/i/1207390/57.jpg","w":1280,"h":1941},{"t":"https://b.kontol.online/api/imageV2/i/1207390/58.jpg","w":1280,"h":1935},{"t":"https://c.kontol.online/api/imageV2/i/1207390/59.jpg","w":1280,"h":1938},{"t":"https://d.kontol.online/api/imageV2/i/1207390/60.jpg","w":1280,"h":1932},{"t":"https://e.kontol.online/api/imageV2/i/1207390/61.jpg","w":1280,"h":1934},{"t":"https://f.kontol.online/api/imageV2/i/1207390/62.jpg","w":1280,"h":1939},{"t":"https://g.kontol.online/api/imageV2/i/1207390/63.jpg","w":1280,"h":1937},{"t":"https://a.kontol.online/api/imageV2/i/1207390/64.jpg","w":1280,"h":1953},{"t":"https://b.kontol.online/api/imageV2/i/1207390/65.jpg","w":1280,"h":1953},{"t":"https://c.kontol.online/api/imageV2/i/1207390/66.jpg","w":1280,"h":1953},{"t":"https://d.kontol.online/api/imageV2/i/1207390/67.jpg","w":1280,"h":1956},{"t":"https://e.kontol.online/api/imageV2/i/1207390/68.jpg","w":1280,"h":1955},{"t":"https://f.kontol.online/api/imageV2/i/1207390/69.jpg","w":1280,"h":1941},{"t":"https://g.kontol.online/api/imageV2/i/1207390/70.jpg","w":1280,"h":1952},{"t":"https://a.kontol.online/api/imageV2/i/1207390/71.jpg","w":1280,"h":1949},{"t":"https://b.kontol.online/api/imageV2/i/1207390/72.jpg","w":1280,"h":1951},{"t":"https://c.kontol.online/api/imageV2/i/1207390/73.jpg","w":1280,"h":1950},{"t":"https://d.kontol.online/api/imageV2/i/1207390/74.jpg","w":1280,"h":1950},{"t":"https://e.kontol.online/api/imageV2/i/1207390/75.jpg","w":1280,"h":1953},{"t":"https://f.kontol.online/api/imageV2/i/1207390/76.jpg","w":1280,"h":1941},{"t":"https://g.kontol.online/api/imageV2/i/1207390/77.jpg","w":1280,"h":1946},{"t":"https://a.kontol.online/api/imageV2/i/1207390/78.jpg","w":1280,"h":1948},{"t":"https://b.kontol.online/api/imageV2/i/1207390/79.jpg","w":1280,"h":1949},{"t":"https://c.kontol.online/api/imageV2/i/1207390/80.jpg","w":1280,"h":1936},{"t":"https://d.kontol.online/api/imageV2/i/1207390/81.jpg","w":1280,"h":1940},{"t":"https://e.kontol.online/api/imageV2/i/1207390/82.jpg","w":1280,"h":1942},{"t":"https://f.kontol.online/api/imageV2/i/1207390/83.jpg","w":1280,"h":1941},{"t":"https://g.kontol.online/api/imageV2/i/1207390/84.jpg","w":1280,"h":1937},{"t":"https://a.kontol.online/api/imageV2/i/1207390/85.jpg","w":1280,"h":1930},{"t":"https://b.kontol.online/api/imageV2/i/1207390/86.jpg","w":1280,"h":1937},{"t":"https://c.kontol.online/api/imageV2/i/1207390/87.jpg","w":1280,"h":1937},{"t":"https://d.kontol.online/api/imageV2/i/1207390/88.jpg","w":1280,"h":1943},{"t":"https://e.kontol.online/api/imageV2/i/1207390/89.jpg","w":1280,"h":1936},{"t":"https://f.kontol.online/api/imageV2/i/1207390/90.jpg","w":1280,"h":1939},{"t":"https://g.kontol.online/api/imageV2/i/1207390/91.jpg","w":1280,"h":1939},{"t":"https://a.kontol.online/api/imageV2/i/1207390/92.jpg","w":1280,"h":1946},{"t":"https://b.kontol.online/api/imageV2/i/1207390/93.jpg","w":1280,"h":1941},{"t":"https://c.kontol.online/api/imageV2/i/1207390/94.jpg","w":1280,"h":1951},{"t":"https://d.kontol.online/api/imageV2/i/1207390/95.jpg","w":1280,"h":1942},{"t":"https://e.kontol.online/api/imageV2/i/1207390/96.jpg","w":1280,"h":1946},{"t":"https://f.kontol.online/api/imageV2/i/1207390/97.jpg","w":1280,"h":1939},{"t":"https://g.kontol.online/api/imageV2/i/1207390/98.jpg","w":1280,"h":1948},{"t":"https://a.kontol.online/api/imageV2/i/1207390/99.jpg","w":1280,"h":1951},{"t":"https://b.kontol.online/api/imageV2/i/1207390/100.jpg","w":1280,"h":1952},{"t":"https://c.kontol.online/api/imageV2/i/1207390/101.jpg","w":1280,"h":1948},{"t":"https://d.kontol.online/api/imageV2/i/1207390/102.jpg","w":1280,"h":1953},{"t":"https://e.kontol.online/api/imageV2/i/1207390/103.jpg","w":1280,"h":1950},{"t":"https://f.kontol.online/api/imageV2/i/1207390/104.jpg","w":1280,"h":1949},{"t":"https://g.kontol.online/api/imageV2/i/1207390/105.jpg","w":1280,"h":1953},{"t":"https://a.kontol.online/api/imageV2/i/1207390/106.jpg","w":1280,"h":1945},{"t":"https://b.kontol.online/api/imageV2/i/1207390/107.jpg","w":1280,"h":1949},{"t":"https://c.kontol.online/api/imageV2/i/1207390/108.jpg","w":1280,"h":1951},{"t":"https://d.kontol.online/api/imageV2/i/1207390/109.jpg","w":1280,"h":1949},{"t":"https://e.kontol.online/api/imageV2/i/1207390/110.jpg","w":1280,"h":1948},{"t":"https://f.kontol.online/api/imageV2/i/1207390/111.jpg","w":1280,"h":1946},{"t":"https://g.kontol.online/api/imageV2/i/1207390/112.jpg","w":1280,"h":1950},{"t":"https://a.kontol.online/api/imageV2/i/1207390/113.jpg","w":1280,"h":1946},{"t":"https://b.kontol.online/api/imageV2/i/1207390/114.jpg","w":1280,"h":1932},{"t":"https://c.kontol.online/api/imageV2/i/1207390/115.jpg","w":1280,"h":1929},{"t":"https://d.kontol.online/api/imageV2/i/1207390/116.jpg","w":1280,"h":1939},{"t":"https://e.kontol.online/api/imageV2/i/1207390/117.jpg","w":1280,"h":1939},{"t":"https://f.kontol.online/api/imageV2/i/1207390/118.jpg","w":1280,"h":1939},{"t":"https://g.kontol.online/api/imageV2/i/1207390/119.jpg","w":1280,"h":1934},{"t":"https://a.kontol.online/api/imageV2/i/1207390/120.jpg","w":1280,"h":1941},{"t":"https://b.kontol.online/api/imageV2/i/1207390/121.jpg","w":1280,"h":1938},{"t":"https://c.kontol.online/api/imageV2/i/1207390/122.jpg","w":1280,"h":1942},{"t":"https://d.kontol.online/api/imageV2/i/1207390/123.jpg","w":1280,"h":1946},{"t":"https://e.kontol.online/api/imageV2/i/1207390/124.jpg","w":1280,"h":1947},{"t":"https://f.kontol.online/api/imageV2/i/1207390/125.jpg","w":1280,"h":1945},{"t":"https://g.kontol.online/api/imageV2/i/1207390/126.jpg","w":1280,"h":1960},{"t":"https://a.kontol.online/api/imageV2/i/1207390/127.jpg","w":1280,"h":1950},{"t":"https://b.kontol.online/api/imageV2/i/1207390/128.jpg","w":1280,"h":1955},{"t":"https://c.kontol.online/api/imageV2/i/1207390/129.jpg","w":1280,"h":1953},{"t":"https://d.kontol.online/api/imageV2/i/1207390/130.jpg","w":1280,"h":1944},{"t":"https://e.kontol.online/api/imageV2/i/1207390/131.jpg","w":1280,"h":1939},{"t":"https://f.kontol.online/api/imageV2/i/1207390/132.jpg","w":1280,"h":1942},{"t":"https://g.kontol.online/api/imageV2/i/1207390/133.jpg","w":1280,"h":1939},{"t":"https://a.kontol.online/api/imageV2/i/1207390/134.jpg","w":1280,"h":1942},{"t":"https://b.kontol.online/api/imageV2/i/1207390/135.jpg","w":1280,"h":1914},{"t":"https://c.kontol.online/api/imageV2/i/1207390/136.jpg","w":1280,"h":1941},{"t":"https://d.kontol.online/api/imageV2/i/1207390/137.jpg","w":1280,"h":1937},{"t":"https://e.kontol.online/api/imageV2/i/1207390/138.jpg","w":1280,"h":1947},{"t":"https://f.kontol.online/api/imageV2/i/1207390/139.jpg","w":1280,"h":1942},{"t":"https://g.kontol.online/api/imageV2/i/1207390/140.jpg","w":1280,"h":1936},{"t":"https://a.kontol.online/api/imageV2/i/1207390/141.jpg","w":1280,"h":1932},{"t":"https://b.kontol.online/api/imageV2/i/1207390/142.jpg","w":1280,"h":1931},{"t":"https://c.kontol.online/api/imageV2/i/1207390/143.jpg","w":1280,"h":1923},{"t":"https://d.kontol.online/api/imageV2/i/1207390/144.jpg","w":1280,"h":1936},{"t":"https://e.kontol.online/api/imageV2/i/1207390/145.jpg","w":1280,"h":1935},{"t":"https://f.kontol.online/api/imageV2/i/1207390/146.jpg","w":1280,"h":1953},{"t":"https://g.kontol.online/api/imageV2/i/1207390/147.jpg","w":1280,"h":1929},{"t":"https://a.kontol.online/api/imageV2/i/1207390/148.jpg","w":1280,"h":1935},{"t":"https://b.kontol.online/api/imageV2/i/1207390/149.jpg","w":1280,"h":1928},{"t":"https://c.kontol.online/api/imageV2/i/1207390/150.jpg","w":1280,"h":1938},{"t":"https://d.kontol.online/api/imageV2/i/1207390/151.jpg","w":1280,"h":1936},{"t":"https://e.kontol.online/api/imageV2/i/1207390/152.jpg","w":1280,"h":1946},{"t":"https://f.kontol.online/api/imageV2/i/1207390/153.jpg","w":1280,"h":1937},{"t":"https://g.kontol.online/api/imageV2/i/1207390/154.jpg","w":1280,"h":1944},{"t":"https://a.kontol.online/api/imageV2/i/1207390/155.jpg","w":1280,"h":1940},{"t":"https://b.kontol.online/api/imageV2/i/1207390/156.jpg","w":1280,"h":1941},{"t":"https://c.kontol.online/api/imageV2/i/1207390/157.jpg","w":1280,"h":1899},{"t":"https://d.kontol.online/api/imageV2/i/1207390/158.jpg","w":1280,"h":1942},{"t":"https://e.kontol.online/api/imageV2/i/1207390/159.jpg","w":1280,"h":1949},{"t":"https://f.kontol.online/api/imageV2/i/1207390/160.jpg","w":1280,"h":1943},{"t":"https://g.kontol.online/api/imageV2/i/1207390/161.jpg","w":1280,"h":1939},{"t":"https://a.kontol.online/api/imageV2/i/1207390/162.jpg","w":1280,"h":1942},{"t":"https://b.kontol.online/api/imageV2/i/1207390/163.jpg","w":1280,"h":1943},{"t":"https://c.kontol.online/api/imageV2/i/1207390/164.jpg","w":1280,"h":1942},{"t":"https://d.kontol.online/api/imageV2/i/1207390/165.jpg","w":1280,"h":1939},{"t":"https://e.kontol.online/api/imageV2/i/1207390/166.jpg","w":1280,"h":1942},{"t":"https://f.kontol.online/api/imageV2/i/1207390/167.jpg","w":1280,"h":1945},{"t":"https://g.kontol.online/api/imageV2/i/1207390/168.jpg","w":1280,"h":1961},{"t":"https://a.kontol.online/api/imageV2/i/1207390/169.jpg","w":1280,"h":1945},{"t":"https://b.kontol.online/api/imageV2/i/1207390/170.jpg","w":1280,"h":1940},{"t":"https://c.kontol.online/api/imageV2/i/1207390/171.jpg","w":1280,"h":1942},{"t":"https://d.kontol.online/api/imageV2/i/1207390/172.jpg","w":1280,"h":1945},{"t":"https://e.kontol.online/api/imageV2/i/1207390/173.jpg","w":1280,"h":1940},{"t":"https://f.kontol.online/api/imageV2/i/1207390/174.jpg","w":1280,"h":1938},{"t":"https://g.kontol.online/api/imageV2/i/1207390/175.jpg","w":1280,"h":1941},{"t":"https://a.kontol.online/api/imageV2/i/1207390/176.jpg","w":1280,"h":1941},{"t":"https://b.kontol.online/api/imageV2/i/1207390/177.jpg","w":1280,"h":1939},{"t":"https://c.kontol.online/api/imageV2/i/1207390/178.jpg","w":1280,"h":1928},{"t":"https://d.kontol.online/api/imageV2/i/1207390/179.jpg","w":1280,"h":1940},{"t":"https://e.kontol.online/api/imageV2/i/1207390/180.jpg","w":1280,"h":1944},{"t":"https://f.kontol.online/api/imageV2/i/1207390/181.jpg","w":1280,"h":1941},{"t":"https://g.kontol.online/api/imageV2/i/1207390/182.jpg","w":1280,"h":1944},{"t":"https://a.kontol.online/api/imageV2/i/1207390/183.jpg","w":1280,"h":1953},{"t":"https://b.kontol.online/api/imageV2/i/1207390/184.jpg","w":1280,"h":1941},{"t":"https://c.kontol.online/api/imageV2/i/1207390/185.jpg","w":1280,"h":1940},{"t":"https://d.kontol.online/api/imageV2/i/1207390/186.jpg","w":1280,"h":1940},{"t":"https://e.kontol.online/api/imageV2/i/1207390/187.jpg","w":1280,"h":1946},{"t":"https://f.kontol.online/api/imageV2/i/1207390/188.jpg","w":1280,"h":1936},{"t":"https://g.kontol.online/api/imageV2/i/1207390/189.jpg","w":1280,"h":1939},{"t":"https://a.kontol.online/api/imageV2/i/1207390/190.jpg","w":1280,"h":1938},{"t":"https://b.kontol.online/api/imageV2/i/1207390/191.jpg","w":1280,"h":1939},{"t":"https://c.kontol.online/api/imageV2/i/1207390/192.jpg","w":1280,"h":1936},{"t":"https://d.kontol.online/api/imageV2/i/1207390/193.jpg","w":1280,"h":1938},{"t":"https://e.kontol.online/api/imageV2/i/1207390/194.jpg","w":1280,"h":1935},{"t":"https://f.kontol.online/api/imageV2/i/1207390/195.jpg","w":1280,"h":1945},{"t":"https://g.kontol.online/api/imageV2/i/1207390/196.jpg","w":1280,"h":1976},{"t":"https://a.kontol.online/api/imageV2/i/1207390/197.jpg","w":1280,"h":1985},{"t":"https://b.kontol.online/api/imageV2/i/1207390/198.jpg","w":1280,"h":1975},{"t":"https://c.kontol.online/api/imageV2/i/1207390/199.jpg","w":1280,"h":1989},{"t":"https://d.kontol.online/api/imageV2/i/1207390/200.jpg","w":1280,"h":1703},{"t":"https://e.kontol.online/api/imageV2/i/1207390/201.jpg","w":1280,"h":782},{"t":"https://f.kontol.online/api/imageV2/i/1207390/202.jpg","w":1280,"h":1866},{"t":"https://g.kontol.online/api/imageV2/i/1207390/203.jpg","w":1280,"h":1873}],"thumbnail":{"t":"https://a.kontol.online/api/imageV2/t/1207390/thumb.jpg","w":350,"h":150}},"
]